advanced_utils/__init__.py
advanced_utils/logger.py
advanced_utils/random.py
tests/__init__.py
tests/test_logger.py
tests/test_random.py
advanced_utils-0.0.4.dist-info/LICENSE
advanced_utils-0.0.4.dist-info/METADATA
advanced_utils-0.0.4.dist-info/WHEEL
advanced_utils-0.0.4.dist-info/top_level.txt
advanced_utils-0.0.4.dist-info/RECORD
