Metadata-Version: 2.1
Name: advanced-utils
Version: 0.0.4
Summary: No Ifs Ands or Butts
Home-page: UNKNOWN
Author: john zhao
Author-email: zhaoxuan1727@gmail.com
License: GPL
Platform: UNKNOWN
